[{
"MPDKey":"275623",
"Name":"CITIBANK N.A.",
"Address":"GREENWICH STREET, 388",
"postalCode":"10013",
"City":"NEW YORK",
"State":"NY",
"ISOCountry":"US",
"Country":"UNITED STATES OF AMERICA",
"MktSerId":"0008",
"MktDirect":"Y",
"Service":"CPI",
"CountryCode":"US",
"CurrencyCode":"USD"
},
{
"MPDKey":"275623",
"Name":"CITIBANK N.A.",
"Address":"GREENWICH STREET, 388",
"postalCode":"10013",
"City":"NEW YORK",
"State":"NY",
"ISOCountry":"US",
"Country":"UNITED STATES OF AMERICA",
"MktSerId":"021000089",
"MktDirect":"Y",
"Service":"FED",
"CountryCode":"US",
"CurrencyCode":"USD"
},
{
"MPDKey":"275623",
"Name":"CITIBANK N.A.",
"Address":"GREENWICH STREET, 388",
"postalCode":"10013",
"City":"NEW YORK",
"State":"NY",
"ISOCountry":"US",
"Country":"UNITED STATES OF AMERICA",
"MktSerId":"CITIUS33XXX",
"MktDirect":"Y",
"Service":"FIN"
},
{
"MPDKey":"275623",
"Name":"CITIBANK N.A.",
"Address":"GREENWICH STREET, 388",
"postalCode":"10013",
"City":"NEW YORK",
"State":"NY",
"ISOCountry":"US",
"Country":"UNITED STATES OF AMERICA",
"MktSerId":"CITIUS33XXX",
"MktDirect":"Y",
"Service":"G01",
"CurrencyCode":"USD"
},
{
"MPDKey":"4729688",
"Name":"UBS AG STAMFORD BRANCH",
"Address":"WASHINGTON BOULEVARD, 600",
"postalCode":"06901",
"City":"STAMFORD",
"State":"CT",
"ISOCountry":"US",
"Country":"UNITED STATES OF AMERICA",
"MktSerId":"026007993",
"MktDirect":"Y",
"Service":"FED",
"CountryCode":"US",
"CurrencyCode":"USD"
},
{
"MPDKey":"4729688",
"Name":"UBS AG STAMFORD BRANCH",
"Address":"WASHINGTON BOULEVARD, 600",
"postalCode":"06901",
"City":"STAMFORD",
"State":"CT",
"ISOCountry":"US",
"Country":"UNITED STATES OF AMERICA",
"MktSerId":"0799",
"MktDirect":"Y",
"Service":"CPI",
"CountryCode":"US",
"CurrencyCode":"USD"
},
{
"MPDKey":"4729688",
"Name":"UBS AG STAMFORD BRANCH",
"Address":"WASHINGTON BOULEVARD, 600",
"postalCode":"06901",
"City":"STAMFORD",
"State":"CT",
"ISOCountry":"US",
"Country":"UNITED STATES OF AMERICA",
"MktSerId":"UBSWUS33XXX",
"MktDirect":"Y",
"Service":"FIN"
},
{
"MPDKey":"4729688",
"Name":"UBS AG STAMFORD BRANCH",
"Address":"WASHINGTON BOULEVARD, 600",
"postalCode":"06901",
"City":"STAMFORD",
"State":"CT",
"ISOCountry":"US",
"Country":"UNITED STATES OF AMERICA",
"MktSerId":"UBSWUS33XXX",
"MktDirect":"Y",
"Service":"G01",
"CurrencyCode":"USD"
},
{
"MPDKey":"4761920",
"Name":"CITIBANK N.A.",
"Address":"13TH FLOOR CITIGROUP CENTRE 2 2 CANADA SQUARE CANARY WHARF",
"postalCode":"E14 5LB",
"City":"LONDON",
"ISOCountry":"GB",
"Country":"UNITED KINGDOM",
"MktSerId":"185008",
"MktDirect":"Y",
"Service":"STG",
"CountryCode":"GB",
"CurrencyCode":"GBP"
},
{
"MPDKey":"4761920",
"Name":"CITIBANK N.A.",
"Address":"13TH FLOOR CITIGROUP CENTRE 2 2 CANADA SQUARE CANARY WHARF",
"postalCode":"E14 5LB",
"City":"LONDON",
"ISOCountry":"GB",
"Country":"UNITED KINGDOM",
"MktSerId":"89095",
"MktDirect":"Y",
"Service":"PCH",
"CurrencyCode":"CHF"
},
{
"MPDKey":"4761920",
"Name":"CITIBANK N.A.",
"Address":"13TH FLOOR CITIGROUP CENTRE 2 2 CANADA SQUARE CANARY WHARF",
"postalCode":"E14 5LB",
"City":"LONDON",
"ISOCountry":"GB",
"Country":"UNITED KINGDOM",
"MktSerId":"CITIGB2LXXX",
"MktDirect":"Y",
"Service":"FIN"
},
{
"MPDKey":"4761920",
"Name":"CITIBANK N.A.",
"Address":"13TH FLOOR CITIGROUP CENTRE 2 2 CANADA SQUARE CANARY WHARF",
"postalCode":"E14 5LB",
"City":"LONDON",
"ISOCountry":"GB",
"Country":"UNITED KINGDOM",
"MktSerId":"CITIGB2LXXX",
"MktDirect":"Y",
"Service":"G01",
"CurrencyCode":"AED"
},
{
"MPDKey":"4761920",
"Name":"CITIBANK N.A.",
"Address":"13TH FLOOR CITIGROUP CENTRE 2 2 CANADA SQUARE CANARY WHARF",
"postalCode":"E14 5LB",
"City":"LONDON",
"ISOCountry":"GB",
"Country":"UNITED KINGDOM",
"MktSerId":"CITIGB2LXXX",
"MktDirect":"Y",
"Service":"G01",
"CurrencyCode":"AUD"
},
{
"MPDKey":"4761920",
"Name":"CITIBANK N.A.",
"Address":"13TH FLOOR CITIGROUP CENTRE 2 2 CANADA SQUARE CANARY WHARF",
"postalCode":"E14 5LB",
"City":"LONDON",
"ISOCountry":"GB",
"Country":"UNITED KINGDOM",
"MktSerId":"CITIGB2LXXX",
"MktDirect":"Y",
"Service":"G01",
"CurrencyCode":"BGN"
},
{
"MPDKey":"4761920",
"Name":"CITIBANK N.A.",
"Address":"13TH FLOOR CITIGROUP CENTRE 2 2 CANADA SQUARE CANARY WHARF",
"postalCode":"E14 5LB",
"City":"LONDON",
"ISOCountry":"GB",
"Country":"UNITED KINGDOM",
"MktSerId":"CITIGB2LXXX",
"MktDirect":"Y",
"Service":"G01",
"CurrencyCode":"BHD"
},
{
"MPDKey":"4761920",
"Name":"CITIBANK N.A.",
"Address":"13TH FLOOR CITIGROUP CENTRE 2 2 CANADA SQUARE CANARY WHARF",
"postalCode":"E14 5LB",
"City":"LONDON",
"ISOCountry":"GB",
"Country":"UNITED KINGDOM",
"MktSerId":"CITIGB2LXXX",
"MktDirect":"Y",
"Service":"G01",
"CurrencyCode":"CAD"
},
{
"MPDKey":"4761920",
"Name":"CITIBANK N.A.",
"Address":"13TH FLOOR CITIGROUP CENTRE 2 2 CANADA SQUARE CANARY WHARF",
"postalCode":"E14 5LB",
"City":"LONDON",
"ISOCountry":"GB",
"Country":"UNITED KINGDOM",
"MktSerId":"CITIGB2LXXX",
"MktDirect":"Y",
"Service":"G01",
"CurrencyCode":"CHF"
},
{
"MPDKey":"4761920",
"Name":"CITIBANK N.A.",
"Address":"13TH FLOOR CITIGROUP CENTRE 2 2 CANADA SQUARE CANARY WHARF",
"postalCode":"E14 5LB",
"City":"LONDON",
"ISOCountry":"GB",
"Country":"UNITED KINGDOM",
"MktSerId":"CITIGB2LXXX",
"MktDirect":"Y",
"Service":"G01",
"CurrencyCode":"CNY"
},
{
"MPDKey":"4761920",
"Name":"CITIBANK N.A.",
"Address":"13TH FLOOR CITIGROUP CENTRE 2 2 CANADA SQUARE CANARY WHARF",
"postalCode":"E14 5LB",
"City":"LONDON",
"ISOCountry":"GB",
"Country":"UNITED KINGDOM",
"MktSerId":"CITIGB2LXXX",
"MktDirect":"Y",
"Service":"G01",
"CurrencyCode":"CZK"
},
{
"MPDKey":"4761920",
"Name":"CITIBANK N.A.",
"Address":"13TH FLOOR CITIGROUP CENTRE 2 2 CANADA SQUARE CANARY WHARF",
"postalCode":"E14 5LB",
"City":"LONDON",
"ISOCountry":"GB",
"Country":"UNITED KINGDOM",
"MktSerId":"CITIGB2LXXX",
"MktDirect":"Y",
"Service":"G01",
"CurrencyCode":"DKK"
},
{
"MPDKey":"4761920",
"Name":"CITIBANK N.A.",
"Address":"13TH FLOOR CITIGROUP CENTRE 2 2 CANADA SQUARE CANARY WHARF",
"postalCode":"E14 5LB",
"City":"LONDON",
"ISOCountry":"GB",
"Country":"UNITED KINGDOM",
"MktSerId":"CITIGB2LXXX",
"MktDirect":"Y",
"Service":"G01",
"CurrencyCode":"EUR"
},
{
"MPDKey":"4761920",
"Name":"CITIBANK N.A.",
"Address":"13TH FLOOR CITIGROUP CENTRE 2 2 CANADA SQUARE CANARY WHARF",
"postalCode":"E14 5LB",
"City":"LONDON",
"ISOCountry":"GB",
"Country":"UNITED KINGDOM",
"MktSerId":"CITIGB2LXXX",
"MktDirect":"Y",
"Service":"G01",
"CurrencyCode":"GBP"
},
{
"MPDKey":"4761920",
"Name":"CITIBANK N.A.",
"Address":"13TH FLOOR CITIGROUP CENTRE 2 2 CANADA SQUARE CANARY WHARF",
"postalCode":"E14 5LB",
"City":"LONDON",
"ISOCountry":"GB",
"Country":"UNITED KINGDOM",
"MktSerId":"CITIGB2LXXX",
"MktDirect":"Y",
"Service":"G01",
"CurrencyCode":"HKD"
},
{
"MPDKey":"4761920",
"Name":"CITIBANK N.A.",
"Address":"13TH FLOOR CITIGROUP CENTRE 2 2 CANADA SQUARE CANARY WHARF",
"postalCode":"E14 5LB",
"City":"LONDON",
"ISOCountry":"GB",
"Country":"UNITED KINGDOM",
"MktSerId":"CITIGB2LXXX",
"MktDirect":"Y",
"Service":"G01",
"CurrencyCode":"HRK"
},
{
"MPDKey":"4761920",
"Name":"CITIBANK N.A.",
"Address":"13TH FLOOR CITIGROUP CENTRE 2 2 CANADA SQUARE CANARY WHARF",
"postalCode":"E14 5LB",
"City":"LONDON",
"ISOCountry":"GB",
"Country":"UNITED KINGDOM",
"MktSerId":"CITIGB2LXXX",
"MktDirect":"Y",
"Service":"G01",
"CurrencyCode":"HUF"
},
{
"MPDKey":"4761920",
"Name":"CITIBANK N.A.",
"Address":"13TH FLOOR CITIGROUP CENTRE 2 2 CANADA SQUARE CANARY WHARF",
"postalCode":"E14 5LB",
"City":"LONDON",
"ISOCountry":"GB",
"Country":"UNITED KINGDOM",
"MktSerId":"CITIGB2LXXX",
"MktDirect":"Y",
"Service":"G01",
"CurrencyCode":"ILS"
},
{
"MPDKey":"4761920",
"Name":"CITIBANK N.A.",
"Address":"13TH FLOOR CITIGROUP CENTRE 2 2 CANADA SQUARE CANARY WHARF",
"postalCode":"E14 5LB",
"City":"LONDON",
"ISOCountry":"GB",
"Country":"UNITED KINGDOM",
"MktSerId":"CITIGB2LXXX",
"MktDirect":"Y",
"Service":"G01",
"CurrencyCode":"JOD"
},
{
"MPDKey":"4761920",
"Name":"CITIBANK N.A.",
"Address":"13TH FLOOR CITIGROUP CENTRE 2 2 CANADA SQUARE CANARY WHARF",
"postalCode":"E14 5LB",
"City":"LONDON",
"ISOCountry":"GB",
"Country":"UNITED KINGDOM",
"MktSerId":"CITIGB2LXXX",
"MktDirect":"Y",
"Service":"G01",
"CurrencyCode":"JPY"
},
{
"MPDKey":"4761920",
"Name":"CITIBANK N.A.",
"Address":"13TH FLOOR CITIGROUP CENTRE 2 2 CANADA SQUARE CANARY WHARF",
"postalCode":"E14 5LB",
"City":"LONDON",
"ISOCountry":"GB",
"Country":"UNITED KINGDOM",
"MktSerId":"CITIGB2LXXX",
"MktDirect":"Y",
"Service":"G01",
"CurrencyCode":"KWD"
},
{
"MPDKey":"4761920",
"Name":"CITIBANK N.A.",
"Address":"13TH FLOOR CITIGROUP CENTRE 2 2 CANADA SQUARE CANARY WHARF",
"postalCode":"E14 5LB",
"City":"LONDON",
"ISOCountry":"GB",
"Country":"UNITED KINGDOM",
"MktSerId":"CITIGB2LXXX",
"MktDirect":"Y",
"Service":"G01",
"CurrencyCode":"MAD"
},
{
"MPDKey":"4761920",
"Name":"CITIBANK N.A.",
"Address":"13TH FLOOR CITIGROUP CENTRE 2 2 CANADA SQUARE CANARY WHARF",
"postalCode":"E14 5LB",
"City":"LONDON",
"ISOCountry":"GB",
"Country":"UNITED KINGDOM",
"MktSerId":"CITIGB2LXXX",
"MktDirect":"Y",
"Service":"G01",
"CurrencyCode":"MUR"
},
{
"MPDKey":"4761920",
"Name":"CITIBANK N.A.",
"Address":"13TH FLOOR CITIGROUP CENTRE 2 2 CANADA SQUARE CANARY WHARF",
"postalCode":"E14 5LB",
"City":"LONDON",
"ISOCountry":"GB",
"Country":"UNITED KINGDOM",
"MktSerId":"CITIGB2LXXX",
"MktDirect":"Y",
"Service":"G01",
"CurrencyCode":"MXN"
},
{
"MPDKey":"4761920",
"Name":"CITIBANK N.A.",
"Address":"13TH FLOOR CITIGROUP CENTRE 2 2 CANADA SQUARE CANARY WHARF",
"postalCode":"E14 5LB",
"City":"LONDON",
"ISOCountry":"GB",
"Country":"UNITED KINGDOM",
"MktSerId":"CITIGB2LXXX",
"MktDirect":"Y",
"Service":"G01",
"CurrencyCode":"NOK"
},
{
"MPDKey":"4761920",
"Name":"CITIBANK N.A.",
"Address":"13TH FLOOR CITIGROUP CENTRE 2 2 CANADA SQUARE CANARY WHARF",
"postalCode":"E14 5LB",
"City":"LONDON",
"ISOCountry":"GB",
"Country":"UNITED KINGDOM",
"MktSerId":"CITIGB2LXXX",
"MktDirect":"Y",
"Service":"G01",
"CurrencyCode":"NZD"
},
{
"MPDKey":"4761920",
"Name":"CITIBANK N.A.",
"Address":"13TH FLOOR CITIGROUP CENTRE 2 2 CANADA SQUARE CANARY WHARF",
"postalCode":"E14 5LB",
"City":"LONDON",
"ISOCountry":"GB",
"Country":"UNITED KINGDOM",
"MktSerId":"CITIGB2LXXX",
"MktDirect":"Y",
"Service":"G01",
"CurrencyCode":"OMR"
},
{
"MPDKey":"4761920",
"Name":"CITIBANK N.A.",
"Address":"13TH FLOOR CITIGROUP CENTRE 2 2 CANADA SQUARE CANARY WHARF",
"postalCode":"E14 5LB",
"City":"LONDON",
"ISOCountry":"GB",
"Country":"UNITED KINGDOM",
"MktSerId":"CITIGB2LXXX",
"MktDirect":"Y",
"Service":"G01",
"CurrencyCode":"PEN"
},
{
"MPDKey":"4761920",
"Name":"CITIBANK N.A.",
"Address":"13TH FLOOR CITIGROUP CENTRE 2 2 CANADA SQUARE CANARY WHARF",
"postalCode":"E14 5LB",
"City":"LONDON",
"ISOCountry":"GB",
"Country":"UNITED KINGDOM",
"MktSerId":"CITIGB2LXXX",
"MktDirect":"Y",
"Service":"G01",
"CurrencyCode":"PLN"
},
{
"MPDKey":"4761920",
"Name":"CITIBANK N.A.",
"Address":"13TH FLOOR CITIGROUP CENTRE 2 2 CANADA SQUARE CANARY WHARF",
"postalCode":"E14 5LB",
"City":"LONDON",
"ISOCountry":"GB",
"Country":"UNITED KINGDOM",
"MktSerId":"CITIGB2LXXX",
"MktDirect":"Y",
"Service":"G01",
"CurrencyCode":"QAR"
},
{
"MPDKey":"4761920",
"Name":"CITIBANK N.A.",
"Address":"13TH FLOOR CITIGROUP CENTRE 2 2 CANADA SQUARE CANARY WHARF",
"postalCode":"E14 5LB",
"City":"LONDON",
"ISOCountry":"GB",
"Country":"UNITED KINGDOM",
"MktSerId":"CITIGB2LXXX",
"MktDirect":"Y",
"Service":"G01",
"CurrencyCode":"RON"
},
{
"MPDKey":"4761920",
"Name":"CITIBANK N.A.",
"Address":"13TH FLOOR CITIGROUP CENTRE 2 2 CANADA SQUARE CANARY WHARF",
"postalCode":"E14 5LB",
"City":"LONDON",
"ISOCountry":"GB",
"Country":"UNITED KINGDOM",
"MktSerId":"CITIGB2LXXX",
"MktDirect":"Y",
"Service":"G01",
"CurrencyCode":"RUB"
},
{
"MPDKey":"4761920",
"Name":"CITIBANK N.A.",
"Address":"13TH FLOOR CITIGROUP CENTRE 2 2 CANADA SQUARE CANARY WHARF",
"postalCode":"E14 5LB",
"City":"LONDON",
"ISOCountry":"GB",
"Country":"UNITED KINGDOM",
"MktSerId":"CITIGB2LXXX",
"MktDirect":"Y",
"Service":"G01",
"CurrencyCode":"SAR"
},
{
"MPDKey":"4761920",
"Name":"CITIBANK N.A.",
"Address":"13TH FLOOR CITIGROUP CENTRE 2 2 CANADA SQUARE CANARY WHARF",
"postalCode":"E14 5LB",
"City":"LONDON",
"ISOCountry":"GB",
"Country":"UNITED KINGDOM",
"MktSerId":"CITIGB2LXXX",
"MktDirect":"Y",
"Service":"G01",
"CurrencyCode":"SEK"
},
{
"MPDKey":"4761920",
"Name":"CITIBANK N.A.",
"Address":"13TH FLOOR CITIGROUP CENTRE 2 2 CANADA SQUARE CANARY WHARF",
"postalCode":"E14 5LB",
"City":"LONDON",
"ISOCountry":"GB",
"Country":"UNITED KINGDOM",
"MktSerId":"CITIGB2LXXX",
"MktDirect":"Y",
"Service":"G01",
"CurrencyCode":"SGD"
},
{
"MPDKey":"4761920",
"Name":"CITIBANK N.A.",
"Address":"13TH FLOOR CITIGROUP CENTRE 2 2 CANADA SQUARE CANARY WHARF",
"postalCode":"E14 5LB",
"City":"LONDON",
"ISOCountry":"GB",
"Country":"UNITED KINGDOM",
"MktSerId":"CITIGB2LXXX",
"MktDirect":"Y",
"Service":"G01",
"CurrencyCode":"THB"
},
{
"MPDKey":"4761920",
"Name":"CITIBANK N.A.",
"Address":"13TH FLOOR CITIGROUP CENTRE 2 2 CANADA SQUARE CANARY WHARF",
"postalCode":"E14 5LB",
"City":"LONDON",
"ISOCountry":"GB",
"Country":"UNITED KINGDOM",
"MktSerId":"CITIGB2LXXX",
"MktDirect":"Y",
"Service":"G01",
"CurrencyCode":"TND"
},
{
"MPDKey":"4761920",
"Name":"CITIBANK N.A.",
"Address":"13TH FLOOR CITIGROUP CENTRE 2 2 CANADA SQUARE CANARY WHARF",
"postalCode":"E14 5LB",
"City":"LONDON",
"ISOCountry":"GB",
"Country":"UNITED KINGDOM",
"MktSerId":"CITIGB2LXXX",
"MktDirect":"Y",
"Service":"G01",
"CurrencyCode":"TRY"
},
{
"MPDKey":"4761920",
"Name":"CITIBANK N.A.",
"Address":"13TH FLOOR CITIGROUP CENTRE 2 2 CANADA SQUARE CANARY WHARF",
"postalCode":"E14 5LB",
"City":"LONDON",
"ISOCountry":"GB",
"Country":"UNITED KINGDOM",
"MktSerId":"CITIGB2LXXX",
"MktDirect":"Y",
"Service":"G01",
"CurrencyCode":"USD"
},
{
"MPDKey":"4761920",
"Name":"CITIBANK N.A.",
"Address":"13TH FLOOR CITIGROUP CENTRE 2 2 CANADA SQUARE CANARY WHARF",
"postalCode":"E14 5LB",
"City":"LONDON",
"ISOCountry":"GB",
"Country":"UNITED KINGDOM",
"MktSerId":"CITIGB2LXXX",
"MktDirect":"Y",
"Service":"G01",
"CurrencyCode":"ZAR"
},
{
"MPDKey":"5811897",
"Name":"CITIBANK COLOMBIA",
"Address":"EDIFICIO CALLE CRA 9A",
"postalCode":"111831",
"City":"BOGOTA",
"ISOCountry":"CO",
"Country":"COLOMBIA",
"MktSerId":"CITICOBBXXX",
"MktDirect":"Y",
"Service":"FIN"
}]